wandbox/__all__.py
wandbox/__bash__.py
wandbox/__cc__.py
wandbox/__cmake__.py
wandbox/__coffee__.py
wandbox/__cpp__.py
wandbox/__crystal__.py
wandbox/__csharp__.py
wandbox/__cxx__.py
wandbox/__dmd__.py
wandbox/__dub__.py
wandbox/__elixir__.py
wandbox/__erlang__.py
wandbox/__fsharp__.py
wandbox/__ghc__.py
wandbox/__go__.py
wandbox/__groovy__.py
wandbox/__init__.py
wandbox/__java__.py
wandbox/__js__.py
wandbox/__julia__.py
wandbox/__lazyk__.py
wandbox/__lisp__.py
wandbox/__lua__.py
wandbox/__main__.py
wandbox/__nim__.py
wandbox/__ocaml__.py
wandbox/__openssl__.py
wandbox/__pascal__.py
wandbox/__perl__.py
wandbox/__php__.py
wandbox/__pony__.py
wandbox/__python__.py
wandbox/__r__.py
wandbox/__ruby__.py
wandbox/__rust__.py
wandbox/__scala__.py
wandbox/__sql__.py
wandbox/__status__.py
wandbox/__swift__.py
wandbox/__tsc__.py
wandbox/__vim__.py
wandbox/__zig__.py
wandbox/cli.py
wandbox/runner.py
wandbox/utils.py
wandbox/wandbox.py
wandbox/wandbox_compile_response.py
wandbox/wrapper.py
wandbox_api-0.10.0.dist-info/LICENSE
wandbox_api-0.10.0.dist-info/METADATA
wandbox_api-0.10.0.dist-info/WHEEL
wandbox_api-0.10.0.dist-info/entry_points.txt
wandbox_api-0.10.0.dist-info/top_level.txt
wandbox_api-0.10.0.dist-info/RECORD
