Metadata-Version: 2.1
Name: wandbox-api
Version: 0.10.0
Summary: A Python binding to the Wandbox API.
Home-page: https://github.com/srz-zumix/wandbox-api/
Author: srz_zumix
Author-email: zumix.cpp@gmail.com
License: MIT
Keywords: API,Wandbox
Platform: any
Classifier: Development Status :: 4 - Beta
Classifier: Topic :: Utilities
Classifier: License :: OSI Approved :: MIT License
Classifier: Programming Language :: Python
Classifier: Programming Language :: Python :: 3.7
Classifier: Programming Language :: Python :: 3.8
Classifier: Programming Language :: Python :: 3.9
Classifier: Programming Language :: Python :: 3.10
Requires-Python: >3.5
Requires-Dist: requests
Requires-Dist: pyyaml
Requires-Dist: toml
Requires-Dist: ndjson
Provides-Extra: test
Requires-Dist: importlib-metadata (<2,>=0.12) ; extra == 'test'
Requires-Dist: tox ; extra == 'test'
Requires-Dist: tox-pyenv ; extra == 'test'
Requires-Dist: pytest ; extra == 'test'
